vcap/__init__.py
vcap/backend.py
vcap/batch_executor.py
vcap/caching.py
vcap/capsule.py
vcap/deprecation.py
vcap/detection_node.py
vcap/device_mapping.py
vcap/modifiers.py
vcap/node_description.py
vcap/options.py
vcap/stream_state.py
vcap/version.py
vcap/loading/capsule_loading.py
vcap/loading/crypto_utils.py
vcap/loading/errors.py
vcap/loading/import_hacks.py
vcap/loading/vcap_packaging.py
vcap/testing/__init__.py
vcap/testing/capsule_loading.py
vcap/testing/input_output_validation.py
vcap/testing/thread_validation.py
vcap-0.5.7.dist-info/METADATA
vcap-0.5.7.dist-info/WHEEL
vcap-0.5.7.dist-info/top_level.txt
vcap-0.5.7.dist-info/RECORD
